liandan/__init__.py
liandan-0.0.0.dist-info/METADATA
liandan-0.0.0.dist-info/RECORD
liandan-0.0.0.dist-info/WHEEL
liandan-0.0.0.dist-info/top_level.txt
